{"appln_filing_year":2010,"tag":"adopter","count":2,"domain":"Climate","dg":"Climate GR","pv":"Agrifood","pvId":"pv01","ind":"# of patents that are adopters, enablers, pioneers and mavericks","indid":"I12A","sv":"by year","svid":"sv01","patstat_version":"2021b","timestamp":"2023-10-06T15:59:55.648Z"}
{"appln_filing_year":2000,"tag":"maverick","count":3,"domain":"Climate","dg":"Climate GR","pv":"Agrifood","pvId":"pv01","ind":"# of patents that are adopters, enablers, pioneers and mavericks","indid":"I12A","sv":"by year","svid":"sv01","patstat_version":"2021b","timestamp":"2023-10-06T15:59:55.648Z"}
{"appln_filing_year":2016,"tag":"adopter","count":2,"domain":"Climate","dg":"Climate GR","pv":"Agrifood","pvId":"pv01","ind":"# of patents that are adopters, enablers, pioneers and mavericks","indid":"I12A","sv":"by year","svid":"sv01","patstat_version":"2021b","timestamp":"2023-10-06T15:59:55.648Z"}
{"appln_filing_year":2008,"tag":"maverick","count":6,"domain":"Climate","dg":"Climate GR","pv":"Agrifood","pvId":"pv01","ind":"# of patents that are adopters, enablers, pioneers and mavericks","indid":"I12A","sv":"by year","svid":"sv01","patstat_version":"2021b","timestamp":"2023-10-06T15:59:55.648Z"}
{"appln_filing_year":2010,"tag":"enabler","count":2,"domain":"Climate","dg":"Climate GR","pv":"Agrifood","pvId":"pv01","ind":"# of patents that are adopters, enablers, pioneers and mavericks","indid":"I12A","sv":"by year","svid":"sv01","patstat_version":"2021b","timestamp":"2023-10-06T15:59:55.648Z"}
{"appln_filing_year":2013,"tag":"maverick","count":9,"domain":"Climate","dg":"Climate GR","pv":"Agrifood","pvId":"pv01","ind":"# of patents that are adopters, enablers, pioneers and mavericks","indid":"I12A","sv":"by year","svid":"sv01","patstat_version":"2021b","timestamp":"2023-10-06T15:59:55.648Z"}
{"appln_filing_year":2005,"tag":"maverick","count":3,"domain":"Climate","dg":"Climate GR","pv":"Agrifood","pvId":"pv01","ind":"# of patents that are adopters, enablers, pioneers and mavericks","indid":"I12A","sv":"by year","svid":"sv01","patstat_version":"2021b","timestamp":"2023-10-06T15:59:55.648Z"}
{"appln_filing_year":2015,"tag":"maverick","count":8,"domain":"Climate","dg":"Climate GR","pv":"Agrifood","pvId":"pv01","ind":"# of patents that are adopters, enablers, pioneers and mavericks","indid":"I12A","sv":"by year","svid":"sv01","patstat_version":"2021b","timestamp":"2023-10-06T15:59:55.648Z"}
{"appln_filing_year":2005,"tag":"enabler","count":1,"domain":"Climate","dg":"Climate GR","pv":"Agrifood","pvId":"pv01","ind":"# of patents that are adopters, enablers, pioneers and mavericks","indid":"I12A","sv":"by year","svid":"sv01","patstat_version":"2021b","timestamp":"2023-10-06T15:59:55.648Z"}
{"appln_filing_year":2011,"tag":"maverick","count":8,"domain":"Climate","dg":"Climate GR","pv":"Agrifood","pvId":"pv01","ind":"# of patents that are adopters, enablers, pioneers and mavericks","indid":"I12A","sv":"by year","svid":"sv01","patstat_version":"2021b","timestamp":"2023-10-06T15:59:55.648Z"}
{"appln_filing_year":2007,"tag":"maverick","count":5,"domain":"Climate","dg":"Climate GR","pv":"Agrifood","pvId":"pv01","ind":"# of patents that are adopters, enablers, pioneers and mavericks","indid":"I12A","sv":"by year","svid":"sv01","patstat_version":"2021b","timestamp":"2023-10-06T15:59:55.648Z"}
{"appln_filing_year":2006,"tag":"maverick","count":3,"domain":"Climate","dg":"Climate GR","pv":"Agrifood","pvId":"pv01","ind":"# of patents that are adopters, enablers, pioneers and mavericks","indid":"I12A","sv":"by year","svid":"sv01","patstat_version":"2021b","timestamp":"2023-10-06T15:59:55.648Z"}
{"appln_filing_year":2012,"tag":"adopter","count":1,"domain":"Climate","dg":"Climate GR","pv":"Agrifood","pvId":"pv01","ind":"# of patents that are adopters, enablers, pioneers and mavericks","indid":"I12A","sv":"by year","svid":"sv01","patstat_version":"2021b","timestamp":"2023-10-06T15:59:55.648Z"}
{"appln_filing_year":2000,"tag":"pioneer","count":2,"domain":"Climate","dg":"Climate GR","pv":"Agrifood","pvId":"pv01","ind":"# of patents that are adopters, enablers, pioneers and mavericks","indid":"I12A","sv":"by year","svid":"sv01","patstat_version":"2021b","timestamp":"2023-10-06T15:59:55.648Z"}
{"appln_filing_year":2012,"tag":"enabler","count":1,"domain":"Climate","dg":"Climate GR","pv":"Agrifood","pvId":"pv01","ind":"# of patents that are adopters, enablers, pioneers and mavericks","indid":"I12A","sv":"by year","svid":"sv01","patstat_version":"2021b","timestamp":"2023-10-06T15:59:55.648Z"}
{"appln_filing_year":2012,"tag":"maverick","count":8,"domain":"Climate","dg":"Climate GR","pv":"Agrifood","pvId":"pv01","ind":"# of patents that are adopters, enablers, pioneers and mavericks","indid":"I12A","sv":"by year","svid":"sv01","patstat_version":"2021b","timestamp":"2023-10-06T15:59:55.648Z"}
{"appln_filing_year":2007,"tag":"adopter","count":2,"domain":"Climate","dg":"Climate GR","pv":"Agrifood","pvId":"pv01","ind":"# of patents that are adopters, enablers, pioneers and mavericks","indid":"I12A","sv":"by year","svid":"sv01","patstat_version":"2021b","timestamp":"2023-10-06T15:59:55.648Z"}
{"appln_filing_year":2006,"tag":"adopter","count":1,"domain":"Climate","dg":"Climate GR","pv":"Agrifood","pvId":"pv01","ind":"# of patents that are adopters, enablers, pioneers and mavericks","indid":"I12A","sv":"by year","svid":"sv01","patstat_version":"2021b","timestamp":"2023-10-06T15:59:55.648Z"}
{"appln_filing_year":2007,"tag":"pioneer","count":4,"domain":"Climate","dg":"Climate GR","pv":"Agrifood","pvId":"pv01","ind":"# of patents that are adopters, enablers, pioneers and mavericks","indid":"I12A","sv":"by year","svid":"sv01","patstat_version":"2021b","timestamp":"2023-10-06T15:59:55.648Z"}
{"appln_filing_year":2014,"tag":"adopter","count":2,"domain":"Climate","dg":"Climate GR","pv":"Agrifood","pvId":"pv01","ind":"# of patents that are adopters, enablers, pioneers and mavericks","indid":"I12A","sv":"by year","svid":"sv01","patstat_version":"2021b","timestamp":"2023-10-06T15:59:55.648Z"}
{"appln_filing_year":2008,"tag":"pioneer","count":2,"domain":"Climate","dg":"Climate GR","pv":"Agrifood","pvId":"pv01","ind":"# of patents that are adopters, enablers, pioneers and mavericks","indid":"I12A","sv":"by year","svid":"sv01","patstat_version":"2021b","timestamp":"2023-10-06T15:59:55.648Z"}
{"appln_filing_year":2014,"tag":"maverick","count":5,"domain":"Climate","dg":"Climate GR","pv":"Agrifood","pvId":"pv01","ind":"# of patents that are adopters, enablers, pioneers and mavericks","indid":"I12A","sv":"by year","svid":"sv01","patstat_version":"2021b","timestamp":"2023-10-06T15:59:55.648Z"}
{"appln_filing_year":2002,"tag":"maverick","count":5,"domain":"Climate","dg":"Climate GR","pv":"Agrifood","pvId":"pv01","ind":"# of patents that are adopters, enablers, pioneers and mavericks","indid":"I12A","sv":"by year","svid":"sv01","patstat_version":"2021b","timestamp":"2023-10-06T15:59:55.648Z"}
{"appln_filing_year":2017,"tag":"enabler","count":3,"domain":"Climate","dg":"Climate GR","pv":"Agrifood","pvId":"pv01","ind":"# of patents that are adopters, enablers, pioneers and mavericks","indid":"I12A","sv":"by year","svid":"sv01","patstat_version":"2021b","timestamp":"2023-10-06T15:59:55.648Z"}
{"appln_filing_year":2013,"tag":"enabler","count":1,"domain":"Climate","dg":"Climate GR","pv":"Agrifood","pvId":"pv01","ind":"# of patents that are adopters, enablers, pioneers and mavericks","indid":"I12A","sv":"by year","svid":"sv01","patstat_version":"2021b","timestamp":"2023-10-06T15:59:55.648Z"}
{"appln_filing_year":2010,"tag":"maverick","count":2,"domain":"Climate","dg":"Climate GR","pv":"Agrifood","pvId":"pv01","ind":"# of patents that are adopters, enablers, pioneers and mavericks","indid":"I12A","sv":"by year","svid":"sv01","patstat_version":"2021b","timestamp":"2023-10-06T15:59:55.648Z"}
{"appln_filing_year":2001,"tag":"maverick","count":7,"domain":"Climate","dg":"Climate GR","pv":"Agrifood","pvId":"pv01","ind":"# of patents that are adopters, enablers, pioneers and mavericks","indid":"I12A","sv":"by year","svid":"sv01","patstat_version":"2021b","timestamp":"2023-10-06T15:59:55.648Z"}
{"appln_filing_year":2005,"tag":"adopter","count":2,"domain":"Climate","dg":"Climate GR","pv":"Agrifood","pvId":"pv01","ind":"# of patents that are adopters, enablers, pioneers and mavericks","indid":"I12A","sv":"by year","svid":"sv01","patstat_version":"2021b","timestamp":"2023-10-06T15:59:55.648Z"}
{"appln_filing_year":2004,"tag":"maverick","count":1,"domain":"Climate","dg":"Climate GR","pv":"Agrifood","pvId":"pv01","ind":"# of patents that are adopters, enablers, pioneers and mavericks","indid":"I12A","sv":"by year","svid":"sv01","patstat_version":"2021b","timestamp":"2023-10-06T15:59:55.648Z"}
{"appln_filing_year":2001,"tag":"pioneer","count":2,"domain":"Climate","dg":"Climate GR","pv":"Agrifood","pvId":"pv01","ind":"# of patents that are adopters, enablers, pioneers and mavericks","indid":"I12A","sv":"by year","svid":"sv01","patstat_version":"2021b","timestamp":"2023-10-06T15:59:55.648Z"}
{"appln_filing_year":2016,"tag":"maverick","count":3,"domain":"Climate","dg":"Climate GR","pv":"Agrifood","pvId":"pv01","ind":"# of patents that are adopters, enablers, pioneers and mavericks","indid":"I12A","sv":"by year","svid":"sv01","patstat_version":"2021b","timestamp":"2023-10-06T15:59:55.648Z"}
{"appln_filing_year":2003,"tag":"enabler","count":2,"domain":"Climate","dg":"Climate GR","pv":"Agrifood","pvId":"pv01","ind":"# of patents that are adopters, enablers, pioneers and mavericks","indid":"I12A","sv":"by year","svid":"sv01","patstat_version":"2021b","timestamp":"2023-10-06T15:59:55.648Z"}
{"appln_filing_year":2014,"tag":"enabler","count":1,"domain":"Climate","dg":"Climate GR","pv":"Agrifood","pvId":"pv01","ind":"# of patents that are adopters, enablers, pioneers and mavericks","indid":"I12A","sv":"by year","svid":"sv01","patstat_version":"2021b","timestamp":"2023-10-06T15:59:55.648Z"}
{"appln_filing_year":2013,"tag":"pioneer","count":1,"domain":"Climate","dg":"Climate GR","pv":"Agrifood","pvId":"pv01","ind":"# of patents that are adopters, enablers, pioneers and mavericks","indid":"I12A","sv":"by year","svid":"sv01","patstat_version":"2021b","timestamp":"2023-10-06T15:59:55.648Z"}
{"appln_filing_year":2017,"tag":"maverick","count":5,"domain":"Climate","dg":"Climate GR","pv":"Agrifood","pvId":"pv01","ind":"# of patents that are adopters, enablers, pioneers and mavericks","indid":"I12A","sv":"by year","svid":"sv01","patstat_version":"2021b","timestamp":"2023-10-06T15:59:55.648Z"}
{"appln_filing_year":2009,"tag":"maverick","count":1,"domain":"Climate","dg":"Climate GR","pv":"Agrifood","pvId":"pv01","ind":"# of patents that are adopters, enablers, pioneers and mavericks","indid":"I12A","sv":"by year","svid":"sv01","patstat_version":"2021b","timestamp":"2023-10-06T15:59:55.648Z"}
{"appln_filing_year":2003,"tag":"maverick","count":4,"domain":"Climate","dg":"Climate GR","pv":"Agrifood","pvId":"pv01","ind":"# of patents that are adopters, enablers, pioneers and mavericks","indid":"I12A","sv":"by year","svid":"sv01","patstat_version":"2021b","timestamp":"2023-10-06T15:59:55.648Z"}
{"appln_filing_year":2014,"tag":"pioneer","count":1,"domain":"Climate","dg":"Climate GR","pv":"Agrifood","pvId":"pv01","ind":"# of patents that are adopters, enablers, pioneers and mavericks","indid":"I12A","sv":"by year","svid":"sv01","patstat_version":"2021b","timestamp":"2023-10-06T15:59:55.648Z"}
{"appln_filing_year":2018,"tag":"maverick","count":1,"domain":"Climate","dg":"Climate GR","pv":"Agrifood","pvId":"pv01","ind":"# of patents that are adopters, enablers, pioneers and mavericks","indid":"I12A","sv":"by year","svid":"sv01","patstat_version":"2021b","timestamp":"2023-10-06T15:59:55.648Z"}
{"appln_filing_year":2003,"tag":"pioneer","count":3,"domain":"Climate","dg":"Climate GR","pv":"Agrifood","pvId":"pv01","ind":"# of patents that are adopters, enablers, pioneers and mavericks","indid":"I12A","sv":"by year","svid":"sv01","patstat_version":"2021b","timestamp":"2023-10-06T15:59:55.648Z"}
{"appln_filing_year":2011,"tag":"enabler","count":2,"domain":"Climate","dg":"Climate GR","pv":"Agrifood","pvId":"pv01","ind":"# of patents that are adopters, enablers, pioneers and mavericks","indid":"I12A","sv":"by year","svid":"sv01","patstat_version":"2021b","timestamp":"2023-10-06T15:59:55.648Z"}
